overwatchleagueapi/__init__.py
overwatchleagueapi/api.py
overwatchleagueapi/models/__init__.py
overwatchleagueapi/models/entities.py
overwatch_league_api-0.0.4.dist-info/LICENSE
overwatch_league_api-0.0.4.dist-info/METADATA
overwatch_league_api-0.0.4.dist-info/WHEEL
overwatch_league_api-0.0.4.dist-info/top_level.txt
overwatch_league_api-0.0.4.dist-info/RECORD
